eptools/InvoiceDate.py
eptools/SQLFactory.py
eptools/SalesForceApiIntegration.py
eptools/Test.py
eptools/WindowsServiceBase.py
eptools/__init__.py
eptools/configuration.py
eptools/finalTestHopefully.py
eptools/logger.py
eptools/mail_factory.py
eptools/sf_factory.py
eptools/slack_factory.py
eptools/slacker.py
eptools/db_connector/__init__.py
eptools/db_connector/connection_factory.py
eptools/db_connector/database_manager.py
eptools/db_connector/connectors/__init__.py
eptools/db_connector/connectors/mysql_connector.py
eptools/db_connector/connectors/sql_server_connector.py
eptools/db_connector/credentials/__init__.py
eptools/db_connector/credentials/config_provider.py
eptools/db_connector/credentials/credential_provider.py
eptools/db_connector/credentials/env_provider.py
eptools-8.8.3.dist-info/LICENSE
eptools-8.8.3.dist-info/METADATA
eptools-8.8.3.dist-info/WHEEL
eptools-8.8.3.dist-info/top_level.txt
eptools-8.8.3.dist-info/RECORD
