Metadata-Version: 2.1
Name: eptools
Version: 8.8.3
Summary: EasyPost Tools
Home-page: UNKNOWN
Author: Arno De Decker
Author-email: arno.dedecker@easypost.eu
License: UNKNOWN
Platform: UNKNOWN
Classifier: Programming Language :: Python :: 3
Classifier: License :: OSI Approved :: MIT License
Classifier: Operating System :: OS Independent
Requires-Python: >=3.6
License-File: LICENSE
Requires-Dist: slack-sdk
Requires-Dist: pyodbc
Requires-Dist: holidays
Requires-Dist: O365
Requires-Dist: simple-salesforce
Requires-Dist: sqlalchemy
Requires-Dist: requests
Requires-Dist: pymysql
Requires-Dist: pypiwin32
Requires-Dist: servicemanager
